factools/__init__.py
factools/load.py
factools-0.1.1.dist-info/METADATA
factools-0.1.1.dist-info/WHEEL
factools-0.1.1.dist-info/top_level.txt
factools-0.1.1.dist-info/RECORD
